.mailmap
AUTHORS
CONTRIBUTING.md
ChangeLog
MANIFEST.in
README.rst
requirements.txt
setup.cfg
setup.py
test-requirements.txt
tox.ini
pypi_mirror/__init__.py
pypi_mirror.egg-info/PKG-INFO
pypi_mirror.egg-info/SOURCES.txt
pypi_mirror.egg-info/dependency_links.txt
pypi_mirror.egg-info/entry_points.txt
pypi_mirror.egg-info/not-zip-safe
pypi_mirror.egg-info/requires.txt
pypi_mirror.egg-info/top_level.txt
pypi_mirror/cmd/__init__.py
pypi_mirror/cmd/run_mirror.py