Metadata-Version: 1.1
Name: pypi-mirror
Version: 1.0.0
Summary: Utility to build a partial PyPI mirror
Home-page: http://ci.openstack.org/
Author: OpenStack Infrastructure Team
Author-email: openstack-infra@lists.openstack.org
License: UNKNOWN
Platform: UNKNOWN
Classifier: Intended Audience :: Information Technology
Classifier: Intended Audience :: System Administrators
Classifier: License :: OSI Approved :: Apache Software License
Classifier: Operating System :: POSIX :: Linux
Classifier: Programming Language :: Python
Classifier: Programming Language :: Python :: 2
Classifier: Programming Language :: Python :: 2.7
Classifier: Programming Language :: Python :: 2.6
